<?xml version='1.0' encoding='UTF-8'?>
<!DOCTYPE ManagedAttribute PUBLIC "sailpoint.dtd" "sailpoint.dtd">
<ManagedAttribute attribute="systemAccess" displayName="Blackline - 8929 - Auditor" hash="97d997c7bd746a4ab02bf6d6847aa4319c167a9c" requestable="true" type="Entitlement" value="Blackline - 8929 - Auditor">
  <ApplicationRef>
    <Reference class="sailpoint.object.Application" name="Blackline"/>
  </ApplicationRef>
  <Attributes>
    <Map>
      <entry key="approvalMode" value="Both"/>
      <entry key="sysDescriptions">
        <value>
          <Map>
            <entry key="en_US" value="Requesting this access will give you access to the Blackline - 8929 - Auditor asset in the Blackline Account Reconciliation tool.  Legal Entity: Performance Specialty Products Asturias S.L."/>
          </Map>
        </value>
      </entry>
    </Map>
  </Attributes>
  <Owner>
    <Reference class="sailpoint.object.Identity" name="ce4845"/>
  </Owner>
</ManagedAttribute>