<?xml version='1.0' encoding='UTF-8'?>
<!DOCTYPE ManagedAttribute PUBLIC "sailpoint.dtd" "sailpoint.dtd">
<ManagedAttribute attribute="systemAccess" displayName="Blackline - Latin America - Business Administrator" hash="e7bd40249d0ab903e181f62ec674b0f08f2e7440" requestable="true" type="Entitlement" value="Blackline - Latin America - Business Administrator">
  <ApplicationRef>
    <Reference class="sailpoint.object.Application" name="Blackline"/>
  </ApplicationRef>
  <Attributes>
    <Map>
      <entry key="approvalMode" value="AssetOwnerOnly"/>
      <entry key="sysDescriptions">
        <value>
          <Map>
            <entry key="en_US" value="Requesting this access will give you access to the Blackline - Latin America - Business Administrator asset in the Blackline Account Reconciliation tool."/>
          </Map>
        </value>
      </entry>
    </Map>
  </Attributes>
  <Owner>
    <Reference class="sailpoint.object.Identity" name="ce4845"/>
  </Owner>
</ManagedAttribute>