<?xml version='1.0' encoding='UTF-8'?>
<!DOCTYPE ManagedAttribute PUBLIC "sailpoint.dtd" "sailpoint.dtd">
<ManagedAttribute attribute="systemAccess" displayName="Trial3 - 1132 - System Administrator" hash="2bfabd39362b21fab253d82a34e317692fc9ba4e" requestable="true" type="Entitlement" value="Trial3 - 1132 - System Administrator">
  <ApplicationRef>
    <Reference class="sailpoint.object.Application" name="Trial3"/>
  </ApplicationRef>
  <Attributes>
    <Map>
      <entry key="approvalMode" value="Both"/>
      <entry key="sysDescriptions">
        <value>
          <Map>
            <entry key="en_US" value="Requesting this access will give you access to the Trial3 - 1132 - System Administrator asset in the Trial3 Account Reconciliation tool.  Legal Entity: DuPont (China) Research &amp; Development and Management Co., Ltd."/>
          </Map>
        </value>
      </entry>
    </Map>
  </Attributes>
  <Owner>
    <Reference class="sailpoint.object.Identity" name="ce4845"/>
  </Owner>
</ManagedAttribute>