<?xml version='1.0' encoding='UTF-8'?>
<!DOCTYPE ManagedAttribute PUBLIC "sailpoint.dtd" "sailpoint.dtd">
<ManagedAttribute attribute="systemAccess" displayName="TestNEW - 1474 - Auditor" hash="0ebae133580d19e26763f6b87f986b7b8c9c387a" requestable="true" type="Entitlement" value="TestNEW - 1474 - Auditor">
  <ApplicationRef>
    <Reference class="sailpoint.object.Application" name="TestNEW"/>
  </ApplicationRef>
  <Attributes>
    <Map>
      <entry key="approvalMode" value="Both"/>
      <entry key="sysDescriptions">
        <value>
          <Map>
            <entry key="en_US" value="Requesting this access will give you access to the TestNEW - 1474 - Auditor asset in the TestNEW Account Reconciliation tool.  Legal Entity: Danisco Dis Ticaret Limited Sirketi."/>
          </Map>
        </value>
      </entry>
    </Map>
  </Attributes>
  <Owner>
    <Reference class="sailpoint.object.Identity" name="TestNEW-Grantors-Workgroup"/>
  </Owner>
</ManagedAttribute>