<?xml version='1.0' encoding='UTF-8'?>
<!DOCTYPE ManagedAttribute PUBLIC "sailpoint.dtd" "sailpoint.dtd">
<ManagedAttribute attribute="systemAccess" displayName="TestNEW - 992 - Financial Manager" hash="65e1bc3e73c653d4f5b8ebdd81531f4f67d95e11" requestable="true" type="Entitlement" value="TestNEW - 992 - Financial Manager">
  <ApplicationRef>
    <Reference class="sailpoint.object.Application" name="TestNEW"/>
  </ApplicationRef>
  <Attributes>
    <Map>
      <entry key="approvalMode" value="Both"/>
      <entry key="sysDescriptions">
        <value>
          <Map>
            <entry key="en_US" value="Requesting this access will give you access to the TestNEW - 992 - Financial Manager asset in the TestNEW Account Reconciliation tool.  Legal Entity: ChemConnect"/>
          </Map>
        </value>
      </entry>
    </Map>
  </Attributes>
  <Owner>
    <Reference class="sailpoint.object.Identity" name="TestNEW-Grantors-Workgroup"/>
  </Owner>
</ManagedAttribute>