<?xml version='1.0' encoding='UTF-8'?>
<!DOCTYPE ManagedAttribute PUBLIC "sailpoint.dtd" "sailpoint.dtd">
<ManagedAttribute attribute="systemAccess" displayName="TestNEW - 9521 - Auditor" hash="850dd369063f08d9cf6ed9e1171ee2f6d6c37c98" requestable="true" type="Entitlement" value="TestNEW - 9521 - Auditor">
  <ApplicationRef>
    <Reference class="sailpoint.object.Application" name="TestNEW"/>
  </ApplicationRef>
  <Attributes>
    <Map>
      <entry key="approvalMode" value="Both"/>
      <entry key="sysDescriptions">
        <value>
          <Map>
            <entry key="en_US" value="Requesting this access will give you access to the TestNEW - 9521 - Auditor asset in the TestNEW Account Reconciliation tool.  Legal Entity: IB EMEA Holding B.V."/>
          </Map>
        </value>
      </entry>
    </Map>
  </Attributes>
  <Owner>
    <Reference class="sailpoint.object.Identity" name="TestNEW-Grantors-Workgroup"/>
  </Owner>
</ManagedAttribute>