<?xml version='1.0' encoding='UTF-8'?>
<!DOCTYPE ManagedAttribute PUBLIC "sailpoint.dtd" "sailpoint.dtd">
<ManagedAttribute attribute="systemAccess" displayName="TestNEW - 729 - Financial Manager" hash="bd1c4ad25be6d1b02de5234b8bd788d8125bc231" requestable="true" type="Entitlement" value="TestNEW - 729 - Financial Manager">
  <ApplicationRef>
    <Reference class="sailpoint.object.Application" name="TestNEW"/>
  </ApplicationRef>
  <Attributes>
    <Map>
      <entry key="approvalMode" value="Both"/>
      <entry key="sysDescriptions">
        <value>
          <Map>
            <entry key="en_US" value="Requesting this access will give you access to the TestNEW - 729 - Financial Manager asset in the TestNEW Account Reconciliation tool.  Legal Entity: DuPont Teijin Films Netherlands BV"/>
          </Map>
        </value>
      </entry>
    </Map>
  </Attributes>
  <Owner>
    <Reference class="sailpoint.object.Identity" name="TestNEW-Grantors-Workgroup"/>
  </Owner>
</ManagedAttribute>