<?xml version='1.0' encoding='UTF-8'?>
<!DOCTYPE ManagedAttribute PUBLIC "sailpoint.dtd" "sailpoint.dtd">
<ManagedAttribute attribute="systemAccess" displayName="TestNEW - Latin America - Business Administrator" hash="4e02e3445230e7209dad5a2f85498c9fa3c031b3" requestable="true" type="Entitlement" value="TestNEW - Latin America - Business Administrator">
  <ApplicationRef>
    <Reference class="sailpoint.object.Application" name="TestNEW"/>
  </ApplicationRef>
  <Attributes>
    <Map>
      <entry key="approvalMode" value="AssetOwnerOnly"/>
      <entry key="sysDescriptions">
        <value>
          <Map>
            <entry key="en_US" value="Requesting this access will give you access to the TestNEW - Latin America - Business Administrator asset in the TestNEW Account Reconciliation tool."/>
          </Map>
        </value>
      </entry>
    </Map>
  </Attributes>
  <Owner>
    <Reference class="sailpoint.object.Identity" name="TestNEW-Grantors-Workgroup"/>
  </Owner>
</ManagedAttribute>