<?xml version='1.0' encoding='UTF-8'?>
<!DOCTYPE ManagedAttribute PUBLIC "sailpoint.dtd" "sailpoint.dtd">
<ManagedAttribute attribute="systemAccess" displayName="Resolve - 1637 - Business Administrator" hash="7d20bc86663e099208bf09b33de5145dfd99003e" requestable="true" type="Entitlement" value="Resolve - 1637 - Business Administrator">
  <ApplicationRef>
    <Reference class="sailpoint.object.Application" name="Resolve"/>
  </ApplicationRef>
  <Attributes>
    <Map>
      <entry key="approvalMode" value="Both"/>
      <entry key="sysDescriptions">
        <value>
          <Map>
            <entry key="en_US" value="Requesting this access will give you access to the Resolve - 1637 - Business Administrator asset in the Resolve Account Reconciliation tool.  Legal Entity: Pannar Seed Ltda Mozambique"/>
          </Map>
        </value>
      </entry>
    </Map>
  </Attributes>
  <Owner>
    <Reference class="sailpoint.object.Identity" name="ce4845"/>
  </Owner>
</ManagedAttribute>