<?xml version='1.0' encoding='UTF-8'?>
<!DOCTYPE ManagedAttribute PUBLIC "sailpoint.dtd" "sailpoint.dtd">
<ManagedAttribute attribute="systemAccess" displayName="Goddammit - 1456 - Financial Manager" hash="9e9279a51dcd35750b29f0a12088898295dd5875" requestable="true" type="Entitlement" value="Goddammit - 1456 - Financial Manager">
  <ApplicationRef>
    <Reference class="sailpoint.object.Application" name="Goddammit"/>
  </ApplicationRef>
  <Attributes>
    <Map>
      <entry key="approvalMode" value="Both"/>
      <entry key="sysDescriptions">
        <value>
          <Map>
            <entry key="en_US" value="Requesting this access will give you access to the Goddammit - 1456 - Financial Manager asset in the Goddammit Account Reconciliation tool.  Legal Entity: Danisco B.V."/>
          </Map>
        </value>
      </entry>
    </Map>
  </Attributes>
  <Owner>
    <Reference class="sailpoint.object.Identity" name="ce4845"/>
  </Owner>
</ManagedAttribute>