<?xml version='1.0' encoding='UTF-8'?>
<!DOCTYPE ManagedAttribute PUBLIC "sailpoint.dtd" "sailpoint.dtd">
<ManagedAttribute attribute="systemAccess" displayName="Goddammit - 8974 - Approver" hash="f4aba7b62978ffe926762037eff55ab7881c10d2" requestable="true" type="Entitlement" value="Goddammit - 8974 - Approver">
  <ApplicationRef>
    <Reference class="sailpoint.object.Application" name="Goddammit"/>
  </ApplicationRef>
  <Attributes>
    <Map>
      <entry key="approvalMode" value="Both"/>
      <entry key="sysDescriptions">
        <value>
          <Map>
            <entry key="en_US" value="Requesting this access will give you access to the Goddammit - 8974 - Approver asset in the Goddammit Account Reconciliation tool.  Legal Entity: DuPont Specialty Products USA, LLC"/>
          </Map>
        </value>
      </entry>
    </Map>
  </Attributes>
  <Owner>
    <Reference class="sailpoint.object.Identity" name="ce4845"/>
  </Owner>
</ManagedAttribute>