<?xml version='1.0' encoding='UTF-8'?>
<!DOCTYPE ManagedAttribute PUBLIC "sailpoint.dtd" "sailpoint.dtd">
<ManagedAttribute attribute="systemAccess" displayName="SMART - 8567 - Approver" hash="b3d9c8eaa00d839d34c92251c95a8c9b943ce2ca" requestable="true" type="Entitlement" value="SMART - 8567 - Approver">
  <ApplicationRef>
    <Reference class="sailpoint.object.Application" name="SMART"/>
  </ApplicationRef>
  <Attributes>
    <Map>
      <entry key="approvalMode" value="Both"/>
      <entry key="sysDescriptions">
        <value>
          <Map>
            <entry key="en_US" value="Requesting this access will give you access to the SMART - 8567 - Approver asset in the SMART Account Reconciliation tool.  Legal Entity: Purchase Accounting Virtual Entity H&amp;N"/>
          </Map>
        </value>
      </entry>
    </Map>
  </Attributes>
  <Owner>
    <Reference class="sailpoint.object.Identity" name="ce4845"/>
  </Owner>
</ManagedAttribute>