<?xml version='1.0' encoding='UTF-8'?>
<!DOCTYPE ManagedAttribute PUBLIC "sailpoint.dtd" "sailpoint.dtd">
<ManagedAttribute attribute="systemAccess" displayName="SMART - 8563 - System Administrator" hash="08ac5c4db76b98b2eb60bb1c5d39e3c7cd429451" requestable="true" type="Entitlement" value="SMART - 8563 - System Administrator">
  <ApplicationRef>
    <Reference class="sailpoint.object.Application" name="SMART"/>
  </ApplicationRef>
  <Attributes>
    <Map>
      <entry key="approvalMode" value="Both"/>
      <entry key="sysDescriptions">
        <value>
          <Map>
            <entry key="en_US" value="Requesting this access will give you access to the SMART - 8563 - System Administrator asset in the SMART Account Reconciliation tool.  Legal Entity: SP International Holding 5 B.V."/>
          </Map>
        </value>
      </entry>
    </Map>
  </Attributes>
  <Owner>
    <Reference class="sailpoint.object.Identity" name="ce4845"/>
  </Owner>
</ManagedAttribute>