<?xml version='1.0' encoding='UTF-8'?>
<!DOCTYPE ManagedAttribute PUBLIC "sailpoint.dtd" "sailpoint.dtd">
<ManagedAttribute attribute="systemAccess" displayName="SMART - 551 - Business Administrator" hash="a58d57c0a3aa0fe865930b27fe98b508e5b4df6b" requestable="true" type="Entitlement" value="SMART - 551 - Business Administrator">
  <ApplicationRef>
    <Reference class="sailpoint.object.Application" name="SMART"/>
  </ApplicationRef>
  <Attributes>
    <Map>
      <entry key="approvalMode" value="Both"/>
      <entry key="sysDescriptions">
        <value>
          <Map>
            <entry key="en_US" value="Requesting this access will give you access to the SMART - 551 - Business Administrator asset in the SMART Account Reconciliation tool.  Legal Entity: Duwest Nicaragua, S.A."/>
          </Map>
        </value>
      </entry>
    </Map>
  </Attributes>
  <Owner>
    <Reference class="sailpoint.object.Identity" name="ce4845"/>
  </Owner>
</ManagedAttribute>