<?xml version='1.0' encoding='UTF-8'?>
<!DOCTYPE ManagedAttribute PUBLIC "sailpoint.dtd" "sailpoint.dtd">
<ManagedAttribute attribute="systemAccess" displayName="Blackline - 3940 - Auditor" hash="5f200e51f995213e939e1bf2665e6dc6f07db4ff" requestable="true" type="Entitlement" value="Blackline - 3940 - Auditor">
  <ApplicationRef>
    <Reference class="sailpoint.object.Application" name="Blackline"/>
  </ApplicationRef>
  <Attributes>
    <Map>
      <entry key="approvalMode" value="Both"/>
      <entry key="sysDescriptions">
        <value>
          <Map>
            <entry key="en_US" value="Requesting this access will give you access to the Blackline - 3940 - Auditor asset in the Blackline Account Reconciliation tool.  Legal Entity: DuPont Malaysia SDN BHD"/>
          </Map>
        </value>
      </entry>
    </Map>
  </Attributes>
  <Owner>
    <Reference class="sailpoint.object.Identity" name="Blackline-Grantors-Workgroup"/>
  </Owner>
</ManagedAttribute>