<?xml version='1.0' encoding='UTF-8'?>
<!DOCTYPE ManagedAttribute PUBLIC "sailpoint.dtd" "sailpoint.dtd">
<ManagedAttribute attribute="systemAccess" displayName="Blackline - 5681 - Auditor" hash="986dd83d61f01a737c79c3babb9e7ecdff321e6e" requestable="true" type="Entitlement" value="Blackline - 5681 - Auditor">
  <ApplicationRef>
    <Reference class="sailpoint.object.Application" name="Blackline"/>
  </ApplicationRef>
  <Attributes>
    <Map>
      <entry key="approvalMode" value="Both"/>
      <entry key="sysDescriptions">
        <value>
          <Map>
            <entry key="en_US" value="Requesting this access will give you access to the Blackline - 5681 - Auditor asset in the Blackline Account Reconciliation tool.  Legal Entity: DuWest, Inc."/>
          </Map>
        </value>
      </entry>
    </Map>
  </Attributes>
  <Owner>
    <Reference class="sailpoint.object.Identity" name="Blackline-Grantors-Workgroup"/>
  </Owner>
</ManagedAttribute>