<?xml version='1.0' encoding='UTF-8'?>
<!DOCTYPE ManagedAttribute PUBLIC "sailpoint.dtd" "sailpoint.dtd">
<ManagedAttribute attribute="systemAccess" displayName="Blackline - 1251 - Preparer" hash="f6d5b727dd2e5514fc10df8141de0a9c508cd839" requestable="true" type="Entitlement" value="Blackline - 1251 - Preparer">
  <ApplicationRef>
    <Reference class="sailpoint.object.Application" name="Blackline"/>
  </ApplicationRef>
  <Attributes>
    <Map>
      <entry key="approvalMode" value="Both"/>
      <entry key="sysDescriptions">
        <value>
          <Map>
            <entry key="en_US" value="Requesting this access will give you access to the Blackline - 1251 - Preparer asset in the Blackline Account Reconciliation tool.  Legal Entity: DuPont de Ecuador SA"/>
          </Map>
        </value>
      </entry>
    </Map>
  </Attributes>
  <Owner>
    <Reference class="sailpoint.object.Identity" name="Blackline-Grantors-Workgroup"/>
  </Owner>
</ManagedAttribute>