<?xml version='1.0' encoding='UTF-8'?>
<!DOCTYPE ManagedAttribute PUBLIC "sailpoint.dtd" "sailpoint.dtd">
<ManagedAttribute attribute="systemAccess" displayName="Blackline - 8954 - Local Administrator" hash="4e9688968c2a4d6e87ed777f47f1a8b833a813fb" requestable="true" type="Entitlement" value="Blackline - 8954 - Local Administrator">
  <ApplicationRef>
    <Reference class="sailpoint.object.Application" name="Blackline"/>
  </ApplicationRef>
  <Attributes>
    <Map>
      <entry key="approvalMode" value="Both"/>
      <entry key="sysDescriptions">
        <value>
          <Map>
            <entry key="en_US" value="Requesting this access will give you access to the Blackline - 8954 - Local Administrator asset in the Blackline Account Reconciliation tool.  Legal Entity: Performance Materials Argentina S.A.U."/>
          </Map>
        </value>
      </entry>
    </Map>
  </Attributes>
  <Owner>
    <Reference class="sailpoint.object.Identity" name="Blackline-Grantors-Workgroup"/>
  </Owner>
</ManagedAttribute>