<?xml version='1.0' encoding='UTF-8'?>
<!DOCTYPE ManagedAttribute PUBLIC "sailpoint.dtd" "sailpoint.dtd">
<ManagedAttribute attribute="systemAccess" displayName="Whiteline - 1335 - Business Administrator" hash="ceded169e967f9e96ce6598e5d584cb47ebb3777" requestable="true" type="Entitlement" value="Whiteline - 1335 - Business Administrator">
  <ApplicationRef>
    <Reference class="sailpoint.object.Application" name="Whiteline"/>
  </ApplicationRef>
  <Attributes>
    <Map>
      <entry key="approvalMode" value="Both"/>
      <entry key="sysDescriptions">
        <value>
          <Map>
            <entry key="en_US" value="Requesting this access will give you access to the Whiteline - 1335 - Business Administrator asset in the Whiteline Account Reconciliation tool.  Legal Entity: MapShots, Inc."/>
          </Map>
        </value>
      </entry>
    </Map>
  </Attributes>
  <Owner>
    <Reference class="sailpoint.object.Identity" name="ce4845"/>
  </Owner>
</ManagedAttribute>