<?xml version='1.0' encoding='UTF-8'?>
<!DOCTYPE ManagedAttribute PUBLIC "sailpoint.dtd" "sailpoint.dtd">
<ManagedAttribute attribute="systemAccess" displayName="Whiteline - 2350 - Financial Manager" hash="ad67176e34a5ac512bd6f34f237b481c6c4c164e" requestable="true" type="Entitlement" value="Whiteline - 2350 - Financial Manager">
  <ApplicationRef>
    <Reference class="sailpoint.object.Application" name="Whiteline"/>
  </ApplicationRef>
  <Attributes>
    <Map>
      <entry key="approvalMode" value="Both"/>
      <entry key="sysDescriptions">
        <value>
          <Map>
            <entry key="en_US" value="Requesting this access will give you access to the Whiteline - 2350 - Financial Manager asset in the Whiteline Account Reconciliation tool.  Legal Entity: E. I. du Pont de Nemours and Company"/>
          </Map>
        </value>
      </entry>
    </Map>
  </Attributes>
  <Owner>
    <Reference class="sailpoint.object.Identity" name="ce4845"/>
  </Owner>
</ManagedAttribute>