<?xml version='1.0' encoding='UTF-8'?>
<!DOCTYPE ManagedAttribute PUBLIC "sailpoint.dtd" "sailpoint.dtd">
<ManagedAttribute attribute="systemAccess" displayName="Whiteline - 57 - Approver" hash="163530751bf88f9ccef2943c6664a4056d278ca7" requestable="true" type="Entitlement" value="Whiteline - 57 - Approver">
  <ApplicationRef>
    <Reference class="sailpoint.object.Application" name="Whiteline"/>
  </ApplicationRef>
  <Attributes>
    <Map>
      <entry key="approvalMode" value="Both"/>
      <entry key="sysDescriptions">
        <value>
          <Map>
            <entry key="en_US" value="Requesting this access will give you access to the Whiteline - 57 - Approver asset in the Whiteline Account Reconciliation tool.  Legal Entity: DuPont Teijin Films U.S., Limited Partnership"/>
          </Map>
        </value>
      </entry>
    </Map>
  </Attributes>
  <Owner>
    <Reference class="sailpoint.object.Identity" name="ce4845"/>
  </Owner>
</ManagedAttribute>